{
  "Room0": {
    "Description": "MathQuestion",
    "Adjacent": [
      24,
      2,
      2,
      14
    ]
  },
  "Room1": {
    "Description": "MathQuestion",
    "Adjacent": [
      5,
      4,
      21,
      5
    ]
  },
  "Room2": {
    "Description": "MathQuestion",
    "Adjacent": [
      17,
      2,
      14,
      1
    ]
  },
  "Room3": {
    "Description": "MathQuestion",
    "Adjacent": [
      18,
      8,
      3,
      10
    ]
  },
  "Room4": {
    "Description": "MathQuestion",
    "Adjacent": [
      18,
      18,
      8,
      12
    ]
  },
  "Room5": {
    "Description": "DiceRoll",
    "Adjacent": [
      18,
      20,
      20,
      21
    ]
  },
  "Room6": {
    "Description": "DiceRoll",
    "Adjacent": [
      5,
      1,
      17,
      6
    ]
  },
  "Room7": {
    "Description": "MathQuestion",
    "Adjacent": [
      16,
      0,
      20,
      11
    ]
  },
  "Room8": {
    "Description": "MathQuestion",
    "Adjacent": [
      11,
      20,
      14,
      10
    ]
  },
  "Room9": {
    "Description": "MathQuestion",
    "Adjacent": [
      15,
      4,
      15,
      16
    ]
  },
  "Room10": {
    "Description": "MathQuestion",
    "Adjacent": [
      17,
      7,
      15,
      4
    ]
  },
  "Room11": {
    "Description": "DiceRoll",
    "Adjacent": [
      9,
      11,
      17,
      12
    ]
  },
  "Room12": {
    "Description": "MathQuestion",
    "Adjacent": [
      2,
      19,
      6,
      10
    ]
  },
  "Room13": {
    "Description": "MathQuestion",
    "Adjacent": [
      16,
      24,
      12,
      8
    ]
  },
  "Room14": {
    "Description": "DiceRoll",
    "Adjacent": [
      13,
      1,
      20,
      3
    ]
  },
  "Room15": {
    "Description": "MathQuestion",
    "Adjacent": [
      7,
      24,
      8,
      3
    ]
  },
  "Room16": {
    "Description": "MathQuestion",
    "Adjacent": [
      10,
      11,
      8,
      2
    ]
  },
  "Room17": {
    "Description": "MathQuestion",
    "Adjacent": [
      5,
      11,
      17,
      23
    ]
  },
  "Room18": {
    "Description": "MathQuestion",
    "Adjacent": [
      0,
      24,
      16,
      5
    ]
  },
  "Room19": {
    "Description": "MathQuestion",
    "Adjacent": [
      14,
      1,
      18,
      3
    ]
  },
  "Room20": {
    "Description": "DiceRoll",
    "Adjacent": [
      19,
      24,
      4,
      24
    ]
  },
  "Room21": {
    "Description": "MathQuestion",
    "Adjacent": [
      1,
      16,
      2,
      16
    ]
  },
  "Room22": {
    "Description": "MathQuestion",
    "Adjacent": [
      14,
      18,
      24,
      23
    ]
  },
  "Room23": {
    "Description": "MathQuestion",
    "Adjacent": [
      6,
      4,
      16,
      5
    ]
  },
  "Room24": {
    "Description": "MathQuestion",
    "Adjacent": [
      0,
      16,
      13,
      11
    ]
  }
}